azure_ai_inference_plus/__init__.py
azure_ai_inference_plus/client.py
azure_ai_inference_plus/config.py
azure_ai_inference_plus/exceptions.py
azure_ai_inference_plus/utils.py
azure_ai_inference_plus-1.0.4.dist-info/licenses/LICENSE
azure_ai_inference_plus-1.0.4.dist-info/METADATA
azure_ai_inference_plus-1.0.4.dist-info/WHEEL
azure_ai_inference_plus-1.0.4.dist-info/top_level.txt
azure_ai_inference_plus-1.0.4.dist-info/RECORD
