Metadata-Version: 2.4
Name: azure-ai-inference-plus
Version: 1.0.4
Summary: Enhanced wrapper for Azure AI Inference SDK with automatic retry, JSON validation, and reasoning separation
Author: Zach Grimaldi
License-Expression: MIT
Project-URL: Homepage, https://github.com/zpg6/azure-ai-inference-plus
Project-URL: Repository, https://github.com/zpg6/azure-ai-inference-plus.git
Project-URL: Issues, https://github.com/zpg6/azure-ai-inference-plus/issues
Keywords: azure,ai,foundry,inference,retry,json,validation,chat,completions,embeddings,reasoning,deepseek
Classifier: Development Status :: 4 - Beta
Classifier: Intended Audience :: Developers
Classifier: Programming Language :: Python :: 3
Classifier: Programming Language :: Python :: 3.11
Classifier: Programming Language :: Python :: 3.12
Classifier: Programming Language :: Python :: 3.13
Classifier: Topic :: Software Development :: Libraries :: Python Modules
Classifier: Topic :: Scientific/Engineering :: Artificial Intelligence
Classifier: Operating System :: OS Independent
Requires-Python: >=3.11
License-File: LICENSE
Requires-Dist: azure-ai-inference==1.0.0b9
Requires-Dist: azure-core==1.34.0
Provides-Extra: dev
Requires-Dist: build>=1.2.2.post1; extra == "dev"
Requires-Dist: pytest>=6.0; extra == "dev"
Requires-Dist: pytest-asyncio>=0.18.0; extra == "dev"
Requires-Dist: pytest-cov>=2.0; extra == "dev"
Requires-Dist: pytest-mock>=3.0; extra == "dev"
Requires-Dist: black>=22.0; extra == "dev"
Requires-Dist: isort>=5.0; extra == "dev"
Requires-Dist: flake8>=4.0; extra == "dev"
Requires-Dist: mypy>=0.950; extra == "dev"
Requires-Dist: langchain>=0.1.0; extra == "dev"
Requires-Dist: langchain-core>=0.1.0; extra == "dev"
Requires-Dist: langchain-community>=0.3.0; extra == "dev"
Requires-Dist: python-dotenv>=0.19.0; extra == "dev"
Dynamic: license-file
